[
    {
        "name": "入学式",
        "start_date": "2026-04-02",
        "end_date": "2026-04-02",
        "type": "ceremony",
        "note": "入学式"
    },
    {
        "name": "オリエンテーション",
        "start_date": "2026-04-03",
        "end_date": "2026-04-09",
        "type": "orientation",
        "note": "新入生向けオリエンテーション"
    },
    {
        "name": "前期授業開始",
        "start_date": "2026-04-10",
        "end_date": "2026-04-10",
        "type": "class_start",
        "note": "前期授業開始"
    },
    {
        "name": "昭和の日授業実施日",
        "start_date": "2026-04-29",
        "end_date": "2026-04-29",
        "type": "holiday_class",
        "note": "休日に授業実施"
    },
    {
        "name": "昭和の日振替日",
        "start_date": "2026-05-01",
        "end_date": "2026-05-01",
        "type": "holiday_day",
        "note": "4月29日実施分の休日振替日"
    },
    {
        "name": "憲法記念日",
        "start_date": "2026-05-03",
        "end_date": "2026-05-03",
        "type": "holiday_day",
        "note": "休日"
    },
    {
        "name": "みどりの日",
        "start_date": "2026-05-04",
        "end_date": "2026-05-04",
        "type": "holiday_day",
        "note": "休日"
    },
    {
        "name": "こどもの日",
        "start_date": "2026-05-05",
        "end_date": "2026-05-05",
        "type": "holiday_day",
        "note": "休日"
    },
    {
        "name": "振替休日（憲法記念日）",
        "start_date": "2026-05-06",
        "end_date": "2026-05-06",
        "type": "holiday_day",
        "note": "休日"
    },
    {
        "name": "合同体育祭",
        "start_date": "2026-05-24",
        "end_date": "2026-05-24",
        "type": "event",
        "note": "休講"
    },
    {
        "name": "オープンキャンパス",
        "start_date": "2026-06-14",
        "end_date": "2026-06-14",
        "type": "open_campus",
        "note": "鳩山キャンパス"
    },
    {
        "name": "学期末試験期間開始",
        "start_date": "2026-07-09",
        "end_date": "2026-07-22",
        "type": "test-period",
        "note": "鳩山キャンパス"
    },
    {
        "name": "オープンキャンパス",
        "start_date": "2026-07-12",
        "end_date": "2026-07-12",
        "type": "open_campus",
        "note": "鳩山キャンパス"
    },
    {
        "name": "海の日授業実施日",
        "start_date": "2026-07-20",
        "end_date": "2026-07-20",
        "type": "holiday_class",
        "note": "休日に授業実施"
    },
    {
        "name": "海の日振替日",
        "start_date": "2026-08-07",
        "end_date": "2026-08-07",
        "type": "holiday_day",
        "note": "休日"
    },
    {
        "name": "特定科目試験日",
        "start_date": "2026-07-23",
        "end_date": "2026-07-24",
        "type": "exam",
        "note": "授業・補講なし、特定日"
    },
    {
        "name": "一斉休講振替授業日",
        "start_date": "2026-07-25",
        "end_date": "2026-07-28",
        "type": "makeup_class",
        "note": "台風・降雪等による休講の振替"
    },
    {
        "name": "オープンキャンパス",
        "start_date": "2026-08-01",
        "end_date": "2026-08-02",
        "type": "open_campus",
        "note": "鳩山キャンパス"
    },
    {
        "name": "一斉休業期間",
        "start_date": "2026-08-08",
        "end_date": "2026-08-17",
        "type": "vacation",
        "note": "事務室閉室"
    },
    {
        "name": "山の日",
        "start_date": "2026-08-11",
        "end_date": "2026-08-11",
        "type": "holiday_day",
        "note": "休日"
    },
    {
        "name": "前期成績発表",
        "start_date": "2026-09-01",
        "end_date": "2026-09-01",
        "type": "grade",
        "note": "成績発表"
    },
    {
        "name": "創立記念日",
        "start_date": "2026-09-11",
        "end_date": "2026-09-11",
        "type": "holiday_day",
        "note": "休日"
    },
    {
        "name": "後期授業開始",
        "start_date": "2026-09-12",
        "end_date": "2026-09-12",
        "type": "class_start",
        "note": "後期授業開始"
    },
    {
        "name": "前期末卒業式",
        "start_date": "2026-09-19",
        "end_date": "2026-09-19",
        "type": "ceremony",
        "note": "予定"
    },
    {
        "name": "敬老の日授業実施日",
        "start_date": "2026-09-21",
        "end_date": "2026-09-21",
        "type": "holiday_class",
        "note": "休日に授業実施"
    },
    {
        "name": "休日振替日",
        "start_date": "2026-10-02",
        "end_date": "2026-10-02",
        "type": "substitute_day",
        "note": "敬老の日分"
    },
    
    {
        "name": "スポーツの日授業実施日",
        "start_date": "2026-10-12",
        "end_date": "2026-10-12",
        "type": "holiday_class",
        "note": "休日に授業実施"
    },
    {
        "name": "鳩山祭準備日",
        "start_date": "2026-10-29",
        "end_date": "2026-10-30",
        "type": "festival_prepare",
        "note": "休講"
    },
    {
        "name": "鳩山祭",
        "start_date": "2026-10-31",
        "end_date": "2026-11-01",
        "type": "festival",
        "note": "休講",
        "description": "鳩山キャンパスで開催される学園祭"
    },
    {
        "name": "鳩山祭片付日",
        "start_date": "2026-11-02",
        "end_date": "2026-11-03",
        "type": "festival_cleanup",
        "note": "休講"
    },
    {
        "name": "勤労感謝の日授業実施日",
        "start_date": "2026-11-23",
        "end_date": "2026-11-23",
        "type": "holiday_class",
        "note": "休日に授業実施"
    },
    {
        "name": "キャリアイベント",
        "start_date": "2026-12-15",
        "end_date": "2026-12-15",
        "type": "career",
        "note": "卒業生による仕事研究セミナー・休講"
    },
    {
        "name": "休日振替日",
        "start_date": "2026-12-26",
        "end_date": "2026-12-26",
        "type": "substitute_day",
        "note": "国民の休日分"
    },
    {
        "name": "休日振替日",
        "start_date": "2027-01-05",
        "end_date": "2027-01-05",
        "type": "substitute_day",
        "note": "スポーツの日分"
    },
    {
        "name": "休日振替日",
        "start_date": "2027-01-06",
        "end_date": "2027-01-06",
        "type": "substitute_day",
        "note": "勤労感謝の日分"
    },
    {
        "name": "成人の日",
        "start_date": "2027-01-11",
        "end_date": "2027-01-11",
        "type": "ceremony",
        "note": ""
    },
    {
        "name": "特定科目試験日",
        "start_date": "2027-01-13",
        "end_date": "2027-01-14",
        "type": "exam",
        "note": "特定日"
    },
    {
        "name": "大学入学共通テスト",
        "start_date": "2027-01-15",
        "end_date": "2027-01-16",
        "type": "exam",
        "note": "休講"
    },
    {
        "name": "一斉休講振替授業日",
        "start_date": "2027-01-18",
        "end_date": "2027-01-20",
        "type": "makeup_class",
        "note": ""
    },
    {
        "name": "進級発表・卒業発表・後期成績発表",
        "start_date": "2027-03-02",
        "end_date": "2027-03-02",
        "type": "grade",
        "note": ""
    },
    {
        "name": "卒業式",
        "start_date": "2027-03-19",
        "end_date": "2027-03-19",
        "type": "ceremony",
        "note": ""
    }
]